odesolver/__init__.py
odesolver/explicit.py
odesolver/implicit.py
odesolver/roots.py
odesolver/solver.py
odesolver-0.0.1.dist-info/LICENSE
odesolver-0.0.1.dist-info/METADATA
odesolver-0.0.1.dist-info/WHEEL
odesolver-0.0.1.dist-info/top_level.txt
odesolver-0.0.1.dist-info/RECORD
